airflow_provider_ducklake-0.0.8.dist-info/licenses/LICENSE
ducklake_provider/__init__.py
ducklake_provider/hooks/__init__.py
ducklake_provider/hooks/ducklake_hook.py
airflow_provider_ducklake-0.0.8.dist-info/METADATA
airflow_provider_ducklake-0.0.8.dist-info/WHEEL
airflow_provider_ducklake-0.0.8.dist-info/entry_points.txt
airflow_provider_ducklake-0.0.8.dist-info/top_level.txt
airflow_provider_ducklake-0.0.8.dist-info/RECORD
