Metadata-Version: 2.4
Name: airflow-provider-ducklake
Version: 0.0.8
Summary: DuckLake provider for Apache Airflow (based on DuckDB)
Author-email: Your Name <schapman1974@gmail.com>
License: Apache License 2.0
Project-URL: Homepage, https://github.com/schapman1974/airflow-provider-ducklake
Classifier: Framework :: Apache Airflow
Classifier: Framework :: Apache Airflow :: Provider
Requires-Python: >=3.8
License-File: LICENSE
Requires-Dist: apache-airflow>=2.0
Requires-Dist: duckdb>=1.4.1
Dynamic: license-file
